[
  {
    "name": "Scott",
    "avatar": "https://pbs.twimg.com/profile_images/1193551616/Scott_Profile_400x400.JPG",
    "city": "Austin",
    "tz": "America/Matamoros"
  },
  {
    "name": "John H",
    "avatar": "https://secure.gravatar.com/userimage/106602702/4001a370bae58142857b26bb737fcdd9",
    "city": "Austin",
    "tz": "America/Chicago"
  },
  {
    "name": "Roger",
    "avatar": "https://avatars0.githubusercontent.com/u/8877333?v=3&s=466",
    "city": "Austin",
    "tz": "America/Chicago"
  },
  {
    "name": "Dirk",
    "avatar": "https://mojo.redhat.com/profile-image-display.jspa?imageID=3663&size=200",
    "city": "Munich",
    "tz": "Europe/Berlin"
  },
  {
    "name": "Daniel",
    "avatar": "https://mojo.redhat.com/profile-image-display.jspa?imageID=4969&size=1000",
    "city": "Boston",
    "tz": "America/New_York"
  },
  {
    "name": "Christoph",
    "avatar": "https://pbs.twimg.com/profile_images/766228716091506689/37cJLAB1.jpg",
    "city": "Bonn",
    "tz": "Europe/Berlin"
  },
  {
    "name": "Peter",
    "avatar": "https://media.licdn.com/mpr/mpr/shrinknp_400_400/AAEAAQAAAAAAAAk7AAAAJDJjYjEwNzVjLTU3ODUtNDcwMC1hYTJjLWJkOGViNzA2YTBhZA.jpg",
    "city": "Winchester",
    "tz": "Europe/London"
  },
  {
    "name": "Nenad",
    "avatar": "http://bit.ly/2e74D8W",
    "city": "Brno",
    "tz": "Europe/Belgrade"
  },
  {
    "name": "Aaron",
    "avatar": "https://en.gravatar.com/userimage/12182510/cf87b046cafdcf590c657bdaf97e7527.jpeg",
    "city": "Westford",
    "tz": "America/New_York"
  },
  {
    "name": "Brett",
    "avatar": "https://avatars1.githubusercontent.com/u/4692674?v=3&s=466",
    "city": "Austin",
    "tz": "America/Chicago"
  },
  {
    "name": "Chandler",
    "avatar": "https://avatars1.githubusercontent.com/u/4529229?v=3&s=140",
    "city": "Houston",
    "tz": "America/Chicago"
  },
  {
    "name": "Babak",
    "avatar": "https://lh3.googleusercontent.com/SLC1CD5jQEhRVAj3OC3Utxo2N8c1BBp3SMOCTsiGet14EPZOPU4mwD3G8HOZ2j-1vmocvfUW_b0=w3240-h2025-rw-no",
    "city": "Los Angeles",
    "tz": "America/Los_Angeles"
  },
  {
    "name": "Scott McCarty",
    "avatar": "://s.gravatar.com/avatar/983b48fd25d27360ee91ead46c0c912e?s=200",
    "city": "Akron",
    "tz": "America/New_York"
  }
]
